README.txt
setup.py
bitsyblog/__init__.py
bitsyblog/auth_factory.py
bitsyblog/bitsyblog.py
bitsyblog/blog.py
bitsyblog/blogme.py
bitsyblog/calendar.py
bitsyblog/cli.py
bitsyblog/factory.py
bitsyblog/parser.py
bitsyblog/roles.py
bitsyblog/settings.py
bitsyblog/user.py
bitsyblog/utils.py
bitsyblog.egg-info/PKG-INFO
bitsyblog.egg-info/SOURCES.txt
bitsyblog.egg-info/dependency_links.txt
bitsyblog.egg-info/entry_points.txt
bitsyblog.egg-info/not-zip-safe
bitsyblog.egg-info/requires.txt
bitsyblog.egg-info/top_level.txt