Metadata-Version: 1.0
Name: bitsyblog
Version: 2.4.5
Summary: a tiny tiny blog
Home-page: http://k0s.org/blog
Author: Jeff Hammel
Author-email: k0scist@gmail.com
License: GPL
Keywords: blog
Platform: UNKNOWN
